hivtrace/__init__.py
hivtrace/hivtrace.py
hivtrace/hivtraceviz.py
hivtrace/strip_drams.py
hivtrace/true_append.py
hivtrace/rsrc/LANL.FASTA.gz
hivtrace/rsrc/LANL.TN93OUTPUT.csv.gz
hivtrace/web/static/hivtrace.css
hivtrace/web/static/hivtrace.js
hivtrace/web/static/jquery.js
hivtrace/web/static/tour.js
hivtrace/web/static/vendor.js
hivtrace/web/static/vendor.min.js
hivtrace/web/static/css/bootstrap.css
hivtrace/web/static/css/vendor.css
hivtrace/web/static/fonts/fontawesome-webfont.eot
hivtrace/web/static/fonts/fontawesome-webfont.svg
hivtrace/web/static/fonts/fontawesome-webfont.ttf
hivtrace/web/static/fonts/fontawesome-webfont.woff
hivtrace/web/static/fonts/fontawesome-webfont.woff2
hivtrace/web/static/fonts/glyphicons-halflings-regular.eot
hivtrace/web/static/fonts/glyphicons-halflings-regular.svg
hivtrace/web/static/fonts/glyphicons-halflings-regular.ttf
hivtrace/web/static/fonts/glyphicons-halflings-regular.woff
hivtrace/web/static/fonts/glyphicons-halflings-regular.woff2
hivtrace/web/static/workers/lcc.js
hivtrace/web/static/workers/worker-vendor.js
hivtrace/web/templates/results.html
hivtrace-0.10.1.dist-info/licenses/AUTHORS
hivtrace-0.10.1.dist-info/licenses/LICENSE
hivtrace-0.10.1.dist-info/METADATA
hivtrace-0.10.1.dist-info/WHEEL
hivtrace-0.10.1.dist-info/entry_points.txt
hivtrace-0.10.1.dist-info/top_level.txt
hivtrace-0.10.1.dist-info/RECORD
