Metadata-Version: 2.4
Name: hivtrace
Version: 0.10.1
Summary: HIV-TRACE
Home-page: http://www.hivtrace.org
Author: Joel Wertheim, Sergei Pond, and Steven Weaver
Author-email: sweaver@temple.edu
Requires-Python: >=3.10
License-File: LICENSE
License-File: AUTHORS
Requires-Dist: biopython>=1.58
Requires-Dist: hppy>=0.9.9
Requires-Dist: tornado>=4.3
Requires-Dist: hivclustering[edgefiltering]>=1.6.8
Dynamic: author
Dynamic: author-email
Dynamic: home-page
Dynamic: license-file
Dynamic: requires-dist
Dynamic: requires-python
Dynamic: summary
